{
  "bvid": "BV14G1kB5Evp",
  "title": "《崩坏：星穹铁道》动画短片：「你好，世界」",
  "url": "https://www.bilibili.com/video/BV14G1kB5Evp",
  "pubdate": "2025-11-05 12:00:00",
  "category": "动画短片",
  "views": 11291762,
  "likes": 656959,
  "description": "在和美丽的世界告别前，她向未来回首。\n \n光遍洒世间，人们在啼哭中迎来新生。\n再没有遗憾，再没有告别，他们会相逢、拥抱、成长，直至生命与银河相连。\n \n是啊，那是「记忆」无缘亲历的来日。\n但她相信，「开拓」会带着往昔，驶向永恒。\n最后这一页，以全世的爱，她为因果画下「◦」——\n \n如同回环的涟漪，守候在昨日的岁月。\n如同开拓的罗盘，指引明天滚滚向前。\n \n※建议体验3.7版本开拓任务后观看本视频。\n \n插曲：「昔涟 Ripples of Past Reverie」\n中文演唱者：张韶涵\n英文演唱者：Cassie Wei from Mili\n \n中文CV：\n昔涟——宴宁\n \n日文CV：\n昔涟——井上麻里奈\n \n英文CV：\n昔涟——Aiden Dawn\n \n韩文CV：\n昔涟——조경이"
}